{"oplss-2025":{"title":"OPLSS 2025","taxon":"Venue","tags":[],"route":"oplss-2025.xml","metas":{"homepage":"Https://www.cs.uoregon.edu/research/summerschool/summer25/index.php","venue":"Eugene, Oregon"}},"lazarek-et-al-2025":{"title":"From Ahead-of- to Just-in-Time and Back Again: Static Analysis for Unix Shell Programs","taxon":"Reference","tags":[],"route":"lazarek-et-al-2025.xml","metas":{"doi":"10.1145/3713082.3730395","venue":"HotOS XX","bibtex":"@Inproceedings{lazarek2025,\n  author = {Lazarek, Lukas and Jung, Seong-Heon and Lamprou, Evangelos and Li, Zekai and Narsipur, Anirudh and Zhao, Eric and Greenberg, Michael and Kallas, Konstantinos and Mamouras, Konstantinos and Vasilakis, Nikos},\n  title = {From Ahead-of- to Just-in-Time and Back Again: Static Analysis for Unix Shell Programs},\n  year = {2025},\n  isbn = {9798400714757},\n  publisher = {Association for Computing Machinery},\n  address = {New York, NY, USA},\n  url = {https://doi.org/10.1145/3713082.3730395},\n  doi = {10.1145/3713082.3730395},\n  booktitle = {Proceedings of the 2025 Workshop on Hot Topics in Operating Systems},\n  pages = {88–95},\n  numpages = {8},\n  keywords = {Linux, Unix, inference, shell, static analysis, type systems},\n  location = {Banff, AB, Canada},\n  series = {HotOS '25}\n}"}},"zzhaoe-0038":{"title":"At OPLSS 2025","taxon":"News","tags":[],"route":"zzhaoe-0038.xml","metas":{}},"hotos-2025":{"title":"HotOS XX","taxon":"Venue","tags":[],"route":"hotos-2025.xml","metas":{"homepage":"Https://sigops.org/s/conferences/hotos/2025/index.html","venue":"Banff, Alberta, Canada"}},"zzhaoe-0037":{"title":"At HotOS XX","taxon":"News","tags":[],"route":"zzhaoe-0037.xml","metas":{}},"zzhaoe-0029":{"title":"Kakehashi!","taxon":"News","tags":[],"route":"zzhaoe-0029.xml","metas":{}},"zzhaoe-002T":{"title":"Second-hand book sellers to avoid online","taxon":"Musings","tags":[],"route":"zzhaoe-002T.xml","metas":{}},"zzhaoe-002S":{"title":"Metaprogramming literature","taxon":"Musings","tags":["hidden"],"route":"zzhaoe-002S.xml","metas":{}},"zzhaoe-002L":{"title":"頭字説明ゲーム","taxon":null,"tags":[],"route":"zzhaoe-002L.xml","metas":{}},"zzhaoe-002M":{"title":"頭字説明","taxon":null,"tags":[],"route":"zzhaoe-002M.xml","metas":{}},"zzhaoe-002K":{"title":"A Japanese Acronymy","taxon":"Musings","tags":[],"route":"zzhaoe-002K.xml","metas":{}},"zzhaoe-002I":{"title":"On Tom Bombadil as unfallen Adam","taxon":"Musings","tags":[],"route":"zzhaoe-002I.xml","metas":{}},"zzhaoe-002F":{"title":"A somewhat and poorly glossed \"The Battle of Brunanburh\"","taxon":null,"tags":[],"route":"zzhaoe-002F.xml","metas":{}},"zzhaoe-002D":{"title":"The illusory middle landscape","taxon":"Musings","tags":[],"route":"zzhaoe-002D.xml","metas":{}},"adams-et-al-2025":{"title":"Grove: A Bidirectionally Typed Collaborative Structure Editor Calculus","taxon":"Reference","tags":["featured"],"route":"adams-et-al-2025.xml","metas":{"venue":"POPL 2025","doi":"10.1145/3704909","artifact":"Zzhaoe-000Q","pdf":"Adams-et-al-2025/preprint.pdf","bibtex":"@Article{adams2025a,\n  author = {Adams, Michael D. and Griffis, Eric and Porter, Thomas J. and Satish, Sundara Vishnu and Zhao, Eric and Omar, Cyrus},\n  title = {Grove: A Bidirectionally Typed Collaborative Structure Editor Calculus},\n  year = {2025},\n  issue_date = {January 2025},\n  publisher = {Association for Computing Machinery},\n  address = {New York, NY, USA},\n  volume = {9},\n  number = {POPL},\n  url = {https://doi.org/10.1145/3704909},\n  doi = {10.1145/3704909},\n  journal = {Proc. ACM Program. Lang.},\n  month = jan,\n  articleno = {73},\n  numpages = {29},\n  keywords = {CRDTs, collaborative editing, gradual typing, version control systems}\n}"}},"zzhaoe-002B":{"title":"The unwarranted delights","taxon":"Musings","tags":[],"route":"zzhaoe-002B.xml","metas":{}},"zzhaoe-002A":{"title":"We murder to dissect","taxon":"Musings","tags":[],"route":"zzhaoe-002A.xml","metas":{}},"hu-pientka-2025":{"title":"A Dependent Type Theory for Meta-programming with Intensional Analysis","taxon":"Reference","tags":[],"route":"hu-pientka-2025.xml","metas":{"doi":"10.1007/978-3-031-57262-3_3"}},"zzhaoe-003A":{"title":"Grove published at POPL 2025","taxon":"News","tags":[],"route":"zzhaoe-003A.xml","metas":{}},"zzhaoe-0028":{"title":"MS P.1396a & b: correspondence of Nov. 1958","taxon":"Fiction","tags":[],"route":"zzhaoe-0028.xml","metas":{"pdf":"Zzhaoe-0028/correspondence-of-nov-1958.pdf"}},"njpls-2024-12":{"title":"NJPLS December 2024","taxon":"Venue","tags":[],"route":"njpls-2024-12.xml","metas":{"homepage":"Https://njpls.org/dec2024.html","venue":"Cornell Tech, New York, United States"}},"zzhaoe-0026":{"title":"Presented at NJPLS","taxon":"News","tags":[],"route":"zzhaoe-0026.xml","metas":{}},"zzhaoe-0027":{"title":"Sardalifië","taxon":"Fiction","tags":[],"route":"zzhaoe-0027.xml","metas":{"pdf":"Zzhaoe-0027/sardalifie.pdf"}},"zzhaoe-0023":{"title":"Calling Haskell from Rust","taxon":"Musings","tags":[],"route":"zzhaoe-0023.xml","metas":{}},"zzhaoe-002E":{"title":"Poorly modernising \"The Battle of Brunanburh\"","taxon":"Musings","tags":[],"route":"zzhaoe-002E.xml","metas":{}},"zzhaoe-0022":{"title":"Exhaustive pattern matching with regular expressions","taxon":"Musings","tags":[],"route":"zzhaoe-0022.xml","metas":{}},"zzhaoe-0021":{"title":"Relistening to the Lord of the Rings","taxon":"Musings","tags":[],"route":"zzhaoe-0021.xml","metas":{}},"zzhaoe-0016":{"title":"ペット屋に（２）","taxon":"Poem","tags":[],"route":"zzhaoe-0016.xml","metas":{}},"zzhaoe-0014":{"title":"Fonts for obscure Han ideographs","taxon":"Musings","tags":["hidden"],"route":"zzhaoe-0014.xml","metas":{}},"zzhaoe-000Y":{"title":"Utterly illegible Han ideographs","taxon":"Musings","tags":[],"route":"zzhaoe-000Y.xml","metas":{}},"zzhaoe-000X":{"title":"𰻞𰻞麵","taxon":"Recipe","tags":[],"route":"zzhaoe-000X.xml","metas":{}},"zzhaoe-000U":{"title":"Orpheus in Atuan","taxon":"Musings","tags":[],"route":"zzhaoe-000U.xml","metas":{}},"zzhaoe-000N":{"title":"On names","taxon":"Musings","tags":[],"route":"zzhaoe-000N.xml","metas":{}},"zzhaoe-0001":{"title":"About","taxon":null,"tags":[],"route":"zzhaoe-0001.xml","metas":{}},"prelude":{"title":"Prelude","taxon":null,"tags":[],"route":"prelude.xml","metas":{}},"zzhaoe-000F":{"title":"On the original Orpheus","taxon":"Musings","tags":[],"route":"zzhaoe-000F.xml","metas":{}},"zzhaoe-000C":{"title":"「舟を編む」","taxon":"Musings","tags":["books"],"route":"zzhaoe-000C.xml","metas":{}},"zzhaoe-0032":{"title":"Participated in the UniMath summer school","taxon":"News","tags":[],"route":"zzhaoe-0032.xml","metas":{}},"zzhaoe-0033":{"title":"Started my PhD","taxon":"News","tags":[],"route":"zzhaoe-0033.xml","metas":{}},"zzhaoe-000P":{"title":"The Mountains at the Edge of the World","taxon":"Fiction","tags":[],"route":"zzhaoe-000P.xml","metas":{"pdf":"Zzhaoe-000P/the-mountains-at-the-edge-of-the-world.pdf"}},"zzhaoe-000E":{"title":"On The Worm Ouroboros","taxon":"Musings","tags":["books"],"route":"zzhaoe-000E.xml","metas":{}},"zzhaoe-000S":{"title":"Received the NSF Graduate Research Fellowship!","taxon":"News","tags":[],"route":"zzhaoe-000S.xml","metas":{}},"zzhaoe-000T":{"title":"Passed the JLPT N1!","taxon":"News","tags":[],"route":"zzhaoe-000T.xml","metas":{}},"zzhaoe-0031":{"title":"ミシガンの日本語スピーチコンテストで勝利しました","taxon":"News","tags":[],"route":"zzhaoe-0031.xml","metas":{}},"popl-2025":{"title":"POPL 2025","taxon":"Venue","tags":[],"route":"popl-2025.xml","metas":{"homepage":"Https://popl25.sigplan.org","venue":"Denver, Colorado, United States of America"}},"popl-2024":{"title":"POPL 2024","taxon":"Venue","tags":[],"route":"popl-2024.xml","metas":{"homepage":"Https://popl24.sigplan.org","venue":"London, United Kingdom"}},"zzhaoe-000K":{"title":"Wrath","taxon":"Poem","tags":[],"route":"zzhaoe-000K.xml","metas":{}},"zhao-et-al-2024":{"title":"Total Type Error Localization and Recovery with Holes","taxon":"Reference","tags":["distinguished","featured"],"route":"zhao-et-al-2024.xml","metas":{"doi":"10.1145/3632910","venue":"POPL 2024","pdf":"Zhao-et-al-2024/preprint.pdf","slides":"Zhao-et-al-2024/slides.pdf","artifact":"Zzhaoe-000B","bibtex":"@Article{zhao2024,\n  title={Total Type Error Localization and Recovery with Holes},\n  volume={8},\n  issn={2475-1421},\n  doi={10.1145/3632910},\n  number={POPL},\n  journal={Proceedings of the ACM on Programming Languages},\n  author={Zhao, Eric and Maroof, Raef and Dukkipati, Anand and Blinn, Andrew and Pan, Zhiyi and Omar, Cyrus},\n  year={2024},\n  month={Jan},\n  pages={2041–2068},\n  language={en}\n}"}},"hu-pientka-2024":{"title":"A Layered Approach to Intensional Analysis in Type Theory","taxon":"Reference","tags":[],"route":"hu-pientka-2024.xml","metas":{"doi":"10.1145/3707203"}},"joy-2024":{"title":"Adam Unfallen: Cracking the Bombadil Enigma","taxon":"Reference","tags":[],"route":"joy-2024.xml","metas":{"journal":"Mallorn: Issue 65, Winter 2024"}},"zzhaoe-0010":{"title":"EECS 490: Programming Languages (F23, W24)","taxon":"Course","tags":[],"route":"zzhaoe-0010.xml","metas":{"institution":"The University of Michigan"}},"zzhaoe-000Q":{"title":"Grove (Agda)","taxon":"Software","tags":["past"],"route":"zzhaoe-000Q.xml","metas":{"doi":"10.5281/Zenodo.14026532","venue":"POPL 2025","github":"Fplab/grove-agda","bibtex":"@Software{adams_2025b,\n  author = {Adams, Michael D. and Griffis, Eric and Porter, Thomas J. and Satish, Sundara Vishnu and Zhao, Eric and Omar, Cyrus},\n  title = {Artifact for Grove: A Bidirectionally Typed Collaborative Structure Editor Calculus},\n  year = {2025},\n  publisher = {Association for Computing Machinery},\n  url = {https://doi.org/10.5281/zenodo.14026532},\n},"}},"zzhaoe-000A":{"title":"Hazel","taxon":"Software","tags":["past"],"route":"zzhaoe-000A.xml","metas":{"homepage":"Https://hazel.org","github":"Hazelgrove/hazel"}},"zzhaoe-0024":{"title":"Hermit","taxon":"Software","tags":["ongoing"],"route":"zzhaoe-0024.xml","metas":{"github":"Mirryi/hermit"}},"mallorn-65":{"title":"Mallorn: Issue 65, Winter 2024","taxon":"Reference","tags":[],"route":"mallorn-65.xml","metas":{"issn":"0308-6674"}},"mythlore-144":{"title":"Mythlore: Vol. 42, No. 2 (144), Spring/Summer 2024, Special Issue: Fantasy Goes to Hell","taxon":"Reference","tags":[],"route":"mythlore-144.xml","metas":{"external":"Https://dc.swosu.edu/mythlore/vol42/iss2/"}},"harrison-2024":{"title":"On Nothing: Tolkien, Ungoliant, and Anselmian Thought","taxon":"Reference","tags":[],"route":"harrison-2024.xml","metas":{"journal":"Mallorn: Issue 65, Winter 2024"}},"costabile-2024":{"title":"Orpheus and the Harrowing of Hell in the Tale of Beren and Lúthien","taxon":"Reference","tags":[],"route":"costabile-2024.xml","metas":{"external":"Https://dc.swosu.edu/mythlore/vol42/iss2/5/","journal":"Mythlore: Vol. 42, No. 2 (144), Spring/Summer 2024, Special Issue: Fantasy Goes to Hell","bibtex":"@Article{costabile_2024,\n  title={Orpheus and the Harrowing of Hell in the Tale of Beren and Lúthien},\n  volume={42},\n  ISSN={0146-9339},\n  abstractNote={Critics have observed that Beren and Lúthien’s tale is a Christian retelling of the myth of Orpheus and Eurydice. The “Harrowing of Hell” tradition is widespread in Italy as attested by the mosaic of San Marco among others, but it is in France that the Ovid Moralized reconnects it to Orpheus who descended into the Underworld to save Eurydice (an already late antique parallel) and therefore attests a happy ending version of the story that can be found in medieval England and also in various classical sources, perhaps even in the original legend of Orpheus. The apocryphal Harrowing is also a recurring motif in the Anglo-Saxon and Middle English religious poetry that Tolkien studied. In short, Tolkien has a wealth of precedents in giving his Orpheus and Eurydice, i.e. Beren and Lúthien, a happy ending.},\n  number={2 (144)},\n  journal={Mythlore},\n  publisher={Mythopoeic Society},\n  author={Costabile, Giovanni Carmine},\n  year={2024},\n  pages={61–84}\n}"}},"zzhaoe-0025":{"title":"Cabal-foreign-library","taxon":"Software","tags":["ongoing"],"route":"zzhaoe-0025.xml","metas":{"github":"Mirryi/cabal-foreign-library","crate":"Cabal-foreign-library"}},"zzhaoe-000R":{"title":"Presenting at POPL 2024!","taxon":"News","tags":[],"route":"zzhaoe-000R.xml","metas":{}},"zzhaoe-003B":{"title":"TA'ing EECS 490 this year","taxon":"News","tags":[],"route":"zzhaoe-003B.xml","metas":{}},"zzhaoe-0035":{"title":"Study abroad","taxon":"News","tags":[],"route":"zzhaoe-0035.xml","metas":{}},"zzhaoe-0017":{"title":"川柳集","taxon":"Poem","tags":[],"route":"zzhaoe-0017.xml","metas":{}},"zzhaoe-000O":{"title":"The Butler","taxon":"Fiction","tags":[],"route":"zzhaoe-000O.xml","metas":{"pdf":"Zzhaoe-000O/the-butler.pdf"}},"zzhaoe-0015":{"title":"Otter Gets the Mail","taxon":"Fiction","tags":[],"route":"zzhaoe-0015.xml","metas":{"pdf":"Zzhaoe-0015/otter-gets-the-mail.pdf"}},"zzhaoe-0036":{"title":"Received a FLAS","taxon":"News","tags":[],"route":"zzhaoe-0036.xml","metas":{}},"zzhaoe-000L":{"title":"Sorrow","taxon":"Poem","tags":[],"route":"zzhaoe-000L.xml","metas":{}},"zzhaoe-000I":{"title":"The Wise One of the Mud","taxon":"Poem","tags":[],"route":"zzhaoe-000I.xml","metas":{}},"zzhaoe-000M":{"title":"The Ettin's Lament","taxon":"Poem","tags":[],"route":"zzhaoe-000M.xml","metas":{}},"evans-an-introduction-to-old-english":{"title":"An Introduction to Old English","taxon":"Reference","tags":[],"route":"evans-an-introduction-to-old-english.xml","metas":{"isbn":"978-1-603-29653-3"}},"zzhaoe-000B":{"title":"Total Type Error Localization and Recovery with Holes (Agda)","taxon":"Software","tags":["past"],"route":"zzhaoe-000B.xml","metas":{"doi":"10.5281/Zenodo.10129703","venue":"POPL 2024","github":"Hazelgrove/error-localization-agda","bibtex":"@Software{zhao_2023,\n  title = {Artifact for Total Type Error Localization and Recovery with Holes},\n  url = {https://doi.org/10.5281/zenodo.10129703},\n  version = {1.0},\n  publisher = {Zenodo},\n  author = {Zhao, Eric and Maroof, Raef and Dukkipati, Anand and Blinn, Andrew and Pan, Zhiyi and Omar, Cyrus},\n  date = {2023-11},\n  doi = {10.5281/zenodo.10129703},\n}"}},"zzhaoe-000G":{"title":"On bealuwara weorc","taxon":"Musings","tags":[],"route":"zzhaoe-000G.xml","metas":{}},"jang-et-al-2022":{"title":"Mœbius: metaprogramming using contextual types: the stage where system f can pattern match on itself","taxon":"Reference","tags":[],"route":"jang-et-al-2022.xml","metas":{"doi":"10.1145/3498700"}},"zzhaoe-0008":{"title":"Wikichan","taxon":"Software","tags":["archive"],"route":"zzhaoe-0008.xml","metas":{"github":"Mirryi/wikichan"}},"zzhaoe-0009":{"title":"Shelf","taxon":"Software","tags":["archive"],"route":"zzhaoe-0009.xml","metas":{"github":"Mirryi/shelf"}},"zzhaoe-0013":{"title":"Mm","taxon":"Software","tags":["archive"],"route":"zzhaoe-0013.xml","metas":{"homepage":"Https://mirryi.github.io/mm","github":"Mirryi/mm"}},"zzhaoe-0011":{"title":"Mpdnd","taxon":"Software","tags":["past"],"route":"zzhaoe-0011.xml","metas":{"github":"Mirryi/mpdnd","crate":"Mpdnd"}},"zzhaoe-0012":{"title":"Regexp2","taxon":"Software","tags":["archive"],"route":"zzhaoe-0012.xml","metas":{"github":"Mirryi/regexp2"}},"foys-oepf3":{"title":"Old English Poetry in Facsimile 3.0","taxon":"Reference","tags":[],"route":"foys-oepf3.xml","metas":{"doi":"10.21231/T6a2-jt11"}},"zzhaoe-0007":{"title":"Dotfiles","taxon":"Software","tags":["ongoing"],"route":"zzhaoe-0007.xml","metas":{"github":"Mirryi/dotfiles"}},"journal-of-tolkien-research-6-1":{"title":"Journal of Tolkien Research: Vol. 6: Iss. 1","taxon":"Reference","tags":[],"route":"journal-of-tolkien-research-6-1.xml","metas":{"issn":"2471-934X","external":"Https://scholar.valpo.edu/journaloftolkienresearch/vol6/iss1/"}},"beal-2018":{"title":"Who is Tom Bombadil?: Interpreting the Light in Frodo Baggins and Tom Bombadil's Role in the Healing of Traumatic Memory in J.R.R. Tolkien's Lord of the Rings","taxon":"Reference","tags":[],"route":"beal-2018.xml","metas":{"external":"Https://scholar.valpo.edu/journaloftolkienresearch/vol6/iss1/1/","journal":"Journal of Tolkien Research: Vol. 6: Iss. 1"}},"lewis-the-worlds-last-night-and-other-essays":{"title":"The World's Last Night and Other Essays","taxon":"Reference","tags":[],"route":"lewis-the-worlds-last-night-and-other-essays.xml","metas":{"isbn":"978-0-062-64351-3"}},"merkley-2016":{"title":"Quis Tantus Furor? The Servian Question, Gallus, and Orpheus in Georgics 4","taxon":"Reference","tags":[],"route":"merkley-2016.xml","metas":{"external":"Https://scholarsarchive.byu.edu/etd/6238","bibtex":"@Article{merkley_2016,\n  title={Quis Tantus Furor? The Servian Question, Gallus, and Orpheus in Georgics 4},\n  url={https://scholarsarchive.byu.edu/etd/6238},\n  journal={Theses and Dissertations},\n  author={Merkley, Kyle},\n  year={2016},\n  month={Dec}\n}"}},"miura-fune-wo-amu":{"title":"舟を編む","taxon":"Reference","tags":[],"route":"miura-fune-wo-amu.xml","metas":{"isbn":"978-4-334-76880-5"}},"lewis-the-screwtape-letters":{"title":"The Screwtape Letters","taxon":"Reference","tags":[],"route":"lewis-the-screwtape-letters.xml","metas":{"isbn":"978-0-060-65293-7"}},"bosworth-toller-anglo-saxon-dictionary":{"title":"Bosworth Toller's Anglo-Saxon Dictionary","taxon":"Reference","tags":[],"route":"bosworth-toller-anglo-saxon-dictionary.xml","metas":{"external":"Https://bosworthtoller.com","bibtex":"@Misc{bosworth2014_anglo_saxon_dictionary,\n  address={Prague},\n  title={Bosworth Toller's Anglo-Saxon Dictionary},\n  url={https://bosworthtoller.com},\n  note={Original Dictionary Title: An Anglo-Saxon Dictionary, Based on the Manuscript Collections of the Late Joseph Bosworth, D.D., F.R.S. Original Place: London},\n  publisher={Faculty of Arts, Charles University},\n  author={Bosworth, Joseph},\n  editor={Toller, Thomas Northcote and Sean, Christ and Tichy, Ondřej},\n  year={2014},\n  language={en}\n}"}},"the-elder-scrolls-v-skyrim":{"title":"The Elder Scrolls V: Skyrim","taxon":"Reference","tags":[],"route":"the-elder-scrolls-v-skyrim.xml","metas":{}},"lightfoot-2010":{"title":"Fragments","taxon":"Reference","tags":[],"route":"lightfoot-2010.xml","metas":{"doi":"10.4159/DLCL.hermesianax_colophon-fragments.2010","bibtex":"@Misc{lightfoot_2010,\n  title={Fragments},\n  url={http://www.loebclassics.com/view/hermesianax_colophon-fragments/2010/work.xml},\n  doi={10.4159/DLCL.hermesianax_colophon-fragments.2010},\n  publisher={Harvard University Press},\n  author={Hermesianax and Lightfoot, J. L.},\n  year={2010}\n}"}},"nanevski-et-al-2008":{"title":"Contextual modal type theory","taxon":"Reference","tags":[],"route":"nanevski-et-al-2008.xml","metas":{"doi":"10.1145/1352582.1352591"}},"leguin-tehanu":{"title":"Tehanu","taxon":"Reference","tags":[],"route":"leguin-tehanu.xml","metas":{"isbn":"978-0-613-49527-1","bibtex":"@Book{leguin2001_tehanu,\n\ttitle = {Tehanu},\n\tisbn = {978-0-613-49527-1},\n\tpublisher = {Bt Bound},\n\tauthor = {Le Guin, Ursula},\n\tdate = {2001},\n}"}},"leguin-the-other-wind":{"title":"The Other Wind","taxon":"Reference","tags":[],"route":"leguin-the-other-wind.xml","metas":{"isbn":"978-0-441-00993-0","bibtex":"@Book{leguin2003-the-other-wind,\n  location = {New York},\n  title = {The Other Wind},\n  isbn = {978-0-441-00993-0},\n  pagetotal = {211},\n  publisher = {Ace Books},\n  author = {Le Guin, Ursula K.},\n  date = {2003},\n}"}},"tolkien-tales-from-the-perilous-realm":{"title":"Tales from the Perilous Realm","taxon":"Reference","tags":[],"route":"tolkien-tales-from-the-perilous-realm.xml","metas":{"bibtex":"@Book{tolkien_1997,\n  location = {London},\n  title = {Tales from the Perilous Realm},\n  isbn = {978-0-261-10342-9},\n  pagetotal = {178},\n  publisher = {{HarperCollins}},\n  author = {Tolkien, J. R. R.},\n  date = {1997},\n}"}},"heath-1994":{"title":"The Failure of Orpheus","taxon":"Reference","tags":[],"route":"heath-1994.xml","metas":{"doi":"10.2307/284290","bibtex":"@Article{heath_1994,\n  title={The Failure of Orpheus},\n  volume={124},\n  issn={0360-5949},\n  doi={10.2307/284290},\n  journal={Transactions of the American Philological Association (1974-)},\n  publisher={[Johns Hopkins University Press, American Philological Association]},\n  author={Heath, John},\n  year={1994},\n  pages={163–196}\n}"}},"dostoyevsky-crime-and-punishment":{"title":"Crime and Punishment","taxon":"Reference","tags":[],"route":"dostoyevsky-crime-and-punishment.xml","metas":{"isbn":"978-0-679-73450-5"}},"sibley-tales-from-the-perilous-realm-radio-1992":{"title":"Tales from the Perilous Realm (1992 radio series)","taxon":"Reference","tags":[],"route":"sibley-tales-from-the-perilous-realm-radio-1992.xml","metas":{}},"lipton-an-exaltation-of-larks":{"title":"An Exaltation of Larks","taxon":"Reference","tags":[],"route":"lipton-an-exaltation-of-larks.xml","metas":{"bibtex":"@Book{lipton1991_an_exaltation_of_larks,\n  address={New York, N.Y., U.S.A.},\n  edition={The ultimate edition},\n  title={An Exaltation of Larks},\n  isbn={978-0-670-30044-0},\n  publisher={Viking},\n  author={Lipton, James},\n  year={1991},\n  language={eng}\n}"}},"shippey-the-road-to-middle-earth":{"title":"The Road to Middle-Earth","taxon":"Reference","tags":[],"route":"shippey-the-road-to-middle-earth.xml","metas":{}},"niwa-seishi-no-gogen":{"title":"姓氏の語源","taxon":"Reference","tags":[],"route":"niwa-seishi-no-gogen.xml","metas":{"isbn":"978-4-04-061400-7","bibtex":"@Book{niwa_1981,\n  address={東京},\n  edition={初版},\n  series={角川小事典},\n  title={姓氏の語源},\n  isbn={978-4-04-061400-7},\n  publisher={角川書店},\n  author={丹羽基二著},\n  year={1981},\n  collection={角川小事典},\n  language={jpn}\n}"}},"sibley-the-lord-of-the-rings-radio-1981":{"title":"The Lord of the Rings (1981 radio series)","taxon":"Reference","tags":[],"route":"sibley-the-lord-of-the-rings-radio-1981.xml","metas":{}},"tolkien-letters":{"title":"The Letters of J.R.R. Tolkien","taxon":"Reference","tags":[],"route":"tolkien-letters.xml","metas":{"isbn":"0-395-31555-7"}},"moore-knott-the-elements-of-old-english":{"title":"The Elements of Old English, 10th ed.","taxon":"Reference","tags":[],"route":"moore-knott-the-elements-of-old-english.xml","metas":{"isbn":"978-0-911-58622-0"}},"tolkien-the-silmarillion":{"title":"The Silmarillion","taxon":"Reference","tags":[],"route":"tolkien-the-silmarillion.xml","metas":{"isbn":"978-0-04-823139-0","bibtex":"@Book{tolkien_1977,\n  location = {London u.a.},\n  title = {The Silmarillion},\n  isbn = {978-0-04-823139-0},\n  pagetotal = {365},\n  publisher = {Allen \\& Unwin},\n  author = {Tolkien, John R. R. and Tolkien, Christopher},\n  date = {1977},\n  note = {{OCLC}: 630802801},\n}"}},"leguin-the-farthest-shore":{"title":"The Farthest Shore","taxon":"Reference","tags":[],"route":"leguin-the-farthest-shore.xml","metas":{"isbn":"978-0-689-84782-0","bibtex":"@Book{leguin2001_the_farthest_shore,\n  address={New York},\n  series={Earthsea cycle},\n  title={The Farthest Shore},\n  isbn={978-0-689-84782-0},\n  abstractNote={A young prince joins forces with a master wizard on a journey to discover a cause and remedy for the loss of magic in Earthsea. Darkness Threatens to overtake Earthsea. As the world and its wizards are losing their magic, Ged -- powerful Archmage, wizard, and dragonlord -- embarks on a sailing journey with highborn young prince, Arren. They travel far beyond the realm of death to discover the cause of these evil disturbances and to restore magic to a land desperately thirsty for it},\n  publisher={Aladdin Paperbacks},\n  author={Le Guin, Ursula K.},\n  year={2001},\n  language={eng}\n}"}},"eddison-the-worm-ouroboros":{"title":"The Worm Ouroboros","taxon":"Reference","tags":[],"route":"eddison-the-worm-ouroboros.xml","metas":{"isbn":"978-0-345-02001-7"}},"leguin-the-tombs-of-atuan":{"title":"The Tombs of Atuan","taxon":"Reference","tags":[],"route":"leguin-the-tombs-of-atuan.xml","metas":{"isbn":"978-0-689-84536-9","bibtex":"@Book{leguin2001_the_tombs_of_atuan,\n  address={New York., NY},\n  title={The Tombs of Atuan},\n  isbn={978-0-689-84536-9},\n  publisher={Simon Pulse},\n  author={Le Guin, Ursula K.},\n  year={2001},\n  language={eng}\n}"}},"leguin-a-wizard-of-earthsea":{"title":"A Wizard of Earthsea","taxon":"Reference","tags":[],"route":"leguin-a-wizard-of-earthsea.xml","metas":{"isbn":"978-0-547-85139-6","bibtex":"@Book{leguin2012_a_wizard_of_earthsea,\n  address={Boston, Mass.},\n  title={A Wizard of Earthsea},\n  isbn={978-0-547-85139-6},\n  publisher={Houghton Mifflin},\n  author={Le Guin, Ursula K.},\n  year={2012},\n  collection={Earthsea cycle},\n  language={eng}\n}"}},"chadwick-the-early-church":{"title":"The Early Church","taxon":"Reference","tags":[],"route":"chadwick-the-early-church.xml","metas":{"isbn":"978-0-140-23199-4"}},"kilgariff-the-hobbit-radio-1968":{"title":"The Hobbit (1968 radio series)","taxon":"Reference","tags":[],"route":"kilgariff-the-hobbit-radio-1968.xml","metas":{}},"britton-1967":{"title":"\"Bealuwara Weorc\" in the \"Dream of the Rood\"","taxon":"Reference","tags":[],"route":"britton-1967.xml","metas":{"bibtex":"@Article{britton1967_bealuwara_weorc_dream_of_the_rood,\n  title={\"Bealuwara Weorc\" in the \"Dream of the Rood\"},\n  volume={68},\n  issn={0028-3754},\n  number={3},\n  journal={Neuphilologische Mitteilungen},\n  publisher={Modern Language Society},\n  author={Britton, G. C.},\n  year={1967},\n  pages={273–276}\n}"}},"friedman-1965":{"title":"The figure of Orpheus in antiquity and the Middle Ages","taxon":"Reference","tags":[],"route":"friedman-1965.xml","metas":{"doi":"10.25335/378F-2C92","external":"Https://d.lib.msu.edu/etd/9700","bibtex":"@Phdthesis{friedman_1965,\n  title={The figure of Orpheus in antiquity and the Middle Ages},\n  url={https://d.lib.msu.edu/etd/9700},\n  doi={10.25335/378F-2C92},\n  school={Michigan State University},\n  author={Friedman, John Block}\n}"}},"short-the-gospel-according-to-peanuts":{"title":"The Gospel According to Peanuts","taxon":"Reference","tags":[],"route":"short-the-gospel-according-to-peanuts.xml","metas":{"lc":"NC1429.S4387 S5"}},"kroeber-ishi-in-two-worlds":{"title":"Ishi in Two Worlds: A Biography of the Last Wild Indian in North America","taxon":"Reference","tags":[],"route":"kroeber-ishi-in-two-worlds.xml","metas":{"isbn":"978-0-520-00675-1","bibtex":"@Book{kroeber1961_ishi_in_two_worlds,\n  address={Berkley, California},\n  title={Ishi in Two Worlds: A Biography of the Last Wild Indian in North America},\n  isbn={978-0-520-00675-1},\n  publisher={University of California Press},\n  author={Kroeber, Theodora},\n  year={1961},\n  language={eng}\n}"}},"tolkien-the-lord-of-the-rings":{"title":"The Lord of the Rings","taxon":"Reference","tags":[],"route":"tolkien-the-lord-of-the-rings.xml","metas":{}},"tolkien-the-hobbit":{"title":"The Hobbit, or, There and Back Again","taxon":"Reference","tags":[],"route":"tolkien-the-hobbit.xml","metas":{"bibtex":"@Book{tolkien_1937,\n  location = {London},\n  title = {The hobbit, or, There and back again},\n  pagetotal = {310},\n  publisher = {George Allen \\& Unwin Ltd.},\n  author = {Tolkien, J. R. R.},\n  date = {1937},\n}"}},"chesterton-orthodoxy":{"title":"Orthodoxy","taxon":"Reference","tags":[],"route":"chesterton-orthodoxy.xml","metas":{}},"atlas":{"title":"ATLAS","taxon":"Organization","tags":[],"route":"atlas.xml","metas":{"homepage":"Https://atlas.cs.brown.edu/"}},"aleksandarnanevski":{"title":"Aleksandar Nanevski","taxon":"Person","tags":[],"route":"aleksandarnanevski.xml","metas":{}},"alfredkroeber":{"title":"Alfred Kroeber","taxon":"Person","tags":[],"route":"alfredkroeber.xml","metas":{"institution":"University of California, Berkley"}},"alfredtennyson":{"title":"Alfred Tennyson","taxon":"Person","tags":[],"route":"alfredtennyson.xml","metas":{}},"ananddukkipati":{"title":"Anand Dukkipati","taxon":"Person","tags":[],"route":"ananddukkipati.xml","metas":{}},"andrewblinn":{"title":"Andrew Blinn","taxon":"Person","tags":[],"route":"andrewblinn.xml","metas":{"position":"PhD Student","institution":"The University of Michigan","homepage":"Https://andrewblinn.com"}},"anirudhnarsipur":{"title":"Anirudh Narsipur","taxon":"Person","tags":[],"route":"anirudhnarsipur.xml","metas":{"homepage":"Https://anarsipur.com/"}},"ayakasogabe":{"title":"Ayaka Sogabe","taxon":"Person","tags":[],"route":"ayakasogabe.xml","metas":{"original":"曽我部綾香","position":"Lecturer of Japanese","institution":"The University of Michigan","homepage":"Https://lsa.umich.edu/asian/people/faculty/asogabe.html"}},"bethesdagamestudios":{"title":"Bethesda Game Studios","taxon":"Institution","tags":[],"route":"bethesdagamestudios.xml","metas":{}},"briansibley":{"title":"Brian Sibley","taxon":"Person","tags":[],"route":"briansibley.xml","metas":{}},"brigittepientka":{"title":"Brigitte Pientka","taxon":"Person","tags":[],"route":"brigittepientka.xml","metas":{}},"brownuniversity":{"title":"Brown University","taxon":"Institution","tags":[],"route":"brownuniversity.xml","metas":{"homepage":"Https://www.brown.edu"}},"cslewis":{"title":"C.S. Lewis","taxon":"Person","tags":[],"route":"cslewis.xml","metas":{}},"christophertolkien":{"title":"Christopher Tolkien","taxon":"Person","tags":[],"route":"christophertolkien.xml","metas":{}},"cyrusomar":{"title":"Cyrus Omar","taxon":"Person","tags":[],"route":"cyrusomar.xml","metas":{"position":"Assistant Professor of Computer Science","institution":"The University of Michigan","homepage":"Https://web.eecs.umich.edu/~comar/"}},"davidmoon":{"title":"David Moon","taxon":"Person","tags":[],"route":"davidmoon.xml","metas":{"position":"PhD Student","institution":"The University of Michigan"}},"zzhaoe-0030":{"title":"Dostoyevsky describes the PhD","taxon":"Quote","tags":[],"route":"zzhaoe-0030.xml","metas":{"original":"Crime and Punishment"}},"dreamoftherood":{"title":"Dream of the Rood","taxon":"Reference","tags":[],"route":"dreamoftherood.xml","metas":{}},"ereddison":{"title":"E.R. Eddison","taxon":"Person","tags":[],"route":"ereddison.xml","metas":{}},"ericczhao":{"title":"Eric Zhao","taxon":"Person","tags":[],"route":"ericczhao.xml","metas":{"position":"PhD Student","institution":"Brown University","orcid":"0009-0000-4969-2376","github":"Mirryi"}},"ericgriffis":{"title":"Eric Griffis","taxon":"Person","tags":[],"route":"ericgriffis.xml","metas":{}},"ericyzhao":{"title":"Eric Y. Zhao","taxon":"Person","tags":[],"route":"ericyzhao.xml","metas":{"institution":"University of Pennsylvania"}},"frankpfenning":{"title":"Frank Pfenning","taxon":"Person","tags":[],"route":"frankpfenning.xml","metas":{}},"fplab":{"title":"Future of Programming Lab","taxon":"Organization","tags":[],"route":"fplab.xml","metas":{"homepage":"Http://fplab.mplse.org"}},"fyodordostoyevsky":{"title":"Fyodor Dostoyevsky","taxon":"Person","tags":[],"route":"fyodordostoyevsky.xml","metas":{}},"gcbritton":{"title":"G.C. Britton","taxon":"Person","tags":[],"route":"gcbritton.xml","metas":{}},"gilbertchesterton":{"title":"Gilbert K. Chesterton","taxon":"Person","tags":[],"route":"gilbertchesterton.xml","metas":{}},"giovannicostabile":{"title":"Giovanni Costabile","taxon":"Person","tags":[],"route":"giovannicostabile.xml","metas":{}},"henrychadwick":{"title":"Henry Chadwick","taxon":"Person","tags":[],"route":"henrychadwick.xml","metas":{}},"jllightfoot":{"title":"J.L. Lightfoot","taxon":"Person","tags":[],"route":"jllightfoot.xml","metas":{"orcid":"0000-0002-1089-2642","position":"Professor of Greek Literature","institution":"University of Oxford","homepage":"Https://www.classics.ox.ac.uk/people/professor-jane-lightfoot"}},"jrrtolkien":{"title":"J.R.R. Tolkien","taxon":"Person","tags":[],"route":"jrrtolkien.xml","metas":{}},"jackgisondi":{"title":"Jack Gisondi","taxon":"Person","tags":[],"route":"jackgisondi.xml","metas":{}},"jameslipton":{"title":"James Lipton","taxon":"Person","tags":[],"route":"jameslipton.xml","metas":{}},"janebeal":{"title":"Jane Beal","taxon":"Person","tags":[],"route":"janebeal.xml","metas":{"position":"Professor of English","institution":"University of La Verne"}},"jlc":{"title":"Japanese Language Circle","taxon":"Organization","tags":[],"route":"jlc.xml","metas":{"institution":"The University of Michigan","homepage":"Https://linktr.ee/jlcumich"}},"jasonzshu":{"title":"Jason Z. S. Hu","taxon":"Person","tags":[],"route":"jasonzshu.xml","metas":{}},"johnfriedman":{"title":"John Friedman","taxon":"Person","tags":[],"route":"johnfriedman.xml","metas":{}},"johnheath":{"title":"John Heath","taxon":"Person","tags":[],"route":"johnheath.xml","metas":{"position":"Professor of Classics","institution":"Santa Clara University","homepage":"Https://www.scu.edu/cas/classics/faculty-and-staff/john-heath/"}},"jonathanevans":{"title":"Jonathan Evans","taxon":"Person","tags":[],"route":"jonathanevans.xml","metas":{}},"josephbosworth":{"title":"Joseph Bosworth","taxon":"Person","tags":[],"route":"josephbosworth.xml","metas":{}},"junkokondo":{"title":"Junko Kondo","taxon":"Person","tags":[],"route":"junkokondo.xml","metas":{"original":"近藤純子","position":"Instructor of Japanese","institution":"Nanzan University"}},"junyoungjang":{"title":"Junyoung Jang","taxon":"Person","tags":[],"route":"junyoungjang.xml","metas":{}},"konstantinoskallas":{"title":"Konstantinos Kallas","taxon":"Person","tags":[],"route":"konstantinoskallas.xml","metas":{"institution":"University of California Los Angeles","position":"Assistant Professor of Computer Science","homepage":"Https://angelhof.github.io"}},"konstantinosmamouras":{"title":"Konstantinos Mamouras","taxon":"Person","tags":[],"route":"konstantinosmamouras.xml","metas":{"institution":"Rice University","position":"Assistant Professor of Computer Science","homepage":"Https://kmamouras.github.io"}},"kylemerkley":{"title":"Kyle Merkley","taxon":"Person","tags":[],"route":"kylemerkley.xml","metas":{}},"lorddunsany":{"title":"Lord Dunsany","taxon":"Person","tags":[],"route":"lorddunsany.xml","metas":{}},"lukaslazarek":{"title":"Lukas Lazarek","taxon":"Person","tags":[],"route":"lukaslazarek.xml","metas":{"institution":"Brown University","position":"Postdoctoral Associate","homepage":"Https://llazarek.github.io"}},"mhacks-2021":{"title":"MHacks 14","taxon":"Venue","tags":[],"route":"mhacks-2021.xml","metas":{"homepage":"Https://web.archive.org/web/20211021115903/https://mhacks.org/"}},"marchepane":{"title":"Marchepane","taxon":"Bookshop","tags":[],"route":"marchepane.xml","metas":{"venue":"London, United Kingdom","homepage":"Https://marchpanebooks.com/"}},"marcusgozon":{"title":"Marcus Gozon","taxon":"Person","tags":[],"route":"marcusgozon.xml","metas":{"institution":"The University of Michigan","homepage":"Https://mgozon.github.io/"}},"martinfoys":{"title":"Martin Foys","taxon":"Person","tags":[],"route":"martinfoys.xml","metas":{"institution":"University of Wisconsin-Madison","position":"Professor of English","homepage":"Https://martinfoys.wordpress.com/"}},"masaeyasuda":{"title":"Masae Yasuda","taxon":"Person","tags":[],"route":"masaeyasuda.xml","metas":{"original":"安田昌江","position":"Teaching Professor of Japanese","institution":"The University of Michigan","homepage":"Https://lsa.umich.edu/asian/people/faculty/mxyasuda.html"}},"maxsnew":{"title":"Max S. New","taxon":"Person","tags":[],"route":"maxsnew.xml","metas":{"position":"Assistant Professor of Computer Science","institution":"The University of Michigan","homepage":"Https://maxsnew.com"}},"michaeladams":{"title":"Michael D. Adams","taxon":"Person","tags":[],"route":"michaeladams.xml","metas":{"position":"Assistant Professor of Computer Science","orcid":"0000-0003-3160-6972","homepage":"Https://michaeldadams.org/"}},"michaelbakewell":{"title":"Michael Bakewell","taxon":"Person","tags":[],"route":"michaelbakewell.xml","metas":{}},"michaelgreenberg":{"title":"Michael Greenberg","taxon":"Person","tags":[],"route":"michaelgreenberg.xml","metas":{"institution":"Stevens Institute of Technology","position":"Assistant Professor of Computer Science","homepage":"Https://mgree.github.io"}},"michaelkilgariff":{"title":"Michael Kilgariff","taxon":"Person","tags":[],"route":"michaelkilgariff.xml","metas":{}},"mythopoeicsociety":{"title":"Mythopoeic Society","taxon":"Institution","tags":[],"route":"mythopoeicsociety.xml","metas":{"homepage":"Https://mythsoc.org/"}},"nanzan":{"title":"Nanzan University","taxon":"Institution","tags":[],"route":"nanzan.xml","metas":{"homepage":"Https://www.nanzan-u.ac.jp"}},"nyu":{"title":"New York University","taxon":"Institution","tags":[],"route":"nyu.xml","metas":{"homepage":"Https://nyu.edu"}},"nikosvasilakis":{"title":"Nikos Vasilakis","taxon":"Person","tags":[],"route":"nikosvasilakis.xml","metas":{"position":"Assistant Professor of Computer Science","institution":"Brown University","homepage":"Https://nikos.vasilak.is","orcid":"0000-0001-7347-298X"}},"niwamotoji":{"title":"Niwa Motoji","taxon":"Person","tags":[],"route":"niwamotoji.xml","metas":{"original":"丹羽基二著"}},"perryneilharrison":{"title":"Perry Neil Harrison","taxon":"Person","tags":[],"route":"perryneilharrison.xml","metas":{}},"raefmaroof":{"title":"Raef Maroof","taxon":"Person","tags":[],"route":"raefmaroof.xml","metas":{}},"riceuniversity":{"title":"Rice University","taxon":"Institution","tags":[],"route":"riceuniversity.xml","metas":{"homepage":"Https://rice.edu"}},"robertlewis":{"title":"Robert Lewis","taxon":"Person","tags":[],"route":"robertlewis.xml","metas":{"position":"Lecturer of Computer Science","institution":"Brown University","homepage":"Https://robertylewis.com"}},"robertlshort":{"title":"Robert L. Short","taxon":"Person","tags":[],"route":"robertlshort.xml","metas":{}},"stlouisuniversity":{"title":"Saint Louis University","taxon":"Institution","tags":[],"route":"stlouisuniversity.xml","metas":{"homepage":"Https://www.slu.edu/"}},"samuelgelineau":{"title":"Samuel Gélineau","taxon":"Person","tags":[],"route":"samuelgelineau.xml","metas":{}},"samuelmoore":{"title":"Samuel Moore","taxon":"Person","tags":[],"route":"samuelmoore.xml","metas":{}},"seongheonjung":{"title":"Seong-Heon Jung","taxon":"Person","tags":[],"route":"seongheonjung.xml","metas":{"institution":"New York University","position":"PhD Student","homepage":"Https://forthoney.github.io"}},"shionmiura":{"title":"Shion Miura","taxon":"Person","tags":[],"route":"shionmiura.xml","metas":{"original":"三浦しをん"}},"stefanmonnier":{"title":"Stefan Monnier","taxon":"Person","tags":[],"route":"stefanmonnier.xml","metas":{}},"stephenjoy":{"title":"Stephen Joy","taxon":"Person","tags":[],"route":"stephenjoy.xml","metas":{}},"stevensit":{"title":"Stevens Institute of Technology","taxon":"Institution","tags":[],"route":"stevensit.xml","metas":{"homepage":"Https://www.stevens.edu"}},"vishnusatish":{"title":"Sundara Vishnu Satish","taxon":"Person","tags":[],"route":"vishnusatish.xml","metas":{"institution":"The University of Michigan"}},"suparnahande":{"title":"Suparna Hande","taxon":"Person","tags":[],"route":"suparnahande.xml","metas":{"institution":"The University of Michigan"}},"umich":{"title":"The University of Michigan","taxon":"Institution","tags":[],"route":"umich.xml","metas":{"homepage":"Https://umich.edu"}},"theodorakroeber":{"title":"Theodora Kroeber","taxon":"Person","tags":[],"route":"theodorakroeber.xml","metas":{}},"thomasknott":{"title":"Thomas A. Knott","taxon":"Person","tags":[],"route":"thomasknott.xml","metas":{}},"thomasporter":{"title":"Thomas J. Porter","taxon":"Person","tags":[],"route":"thomasporter.xml","metas":{"position":"PhD Student","homepage":"Https://thomasporter522.github.io/"}},"tomshippey":{"title":"Tom Shippey","taxon":"Person","tags":[],"route":"tomshippey.xml","metas":{"homepage":"Https://tomshippey.com/","position":"Professor Emeritus","institution":"Saint Louis University"}},"ucberkley":{"title":"University of California, Berkley","taxon":null,"tags":[],"route":"ucberkley.xml","metas":{"homepage":"Https://berkeley.edu"}},"ucla":{"title":"University of California Los Angeles","taxon":"Institution","tags":[],"route":"ucla.xml","metas":{"homepage":"Https://www.ucla.edu"}},"ulaverne":{"title":"University of La Verne","taxon":"Institution","tags":[],"route":"ulaverne.xml","metas":{"homepage":"Https://laverne.edu/"}},"universityofoxford":{"title":"University of Oxford","taxon":"Institution","tags":[],"route":"universityofoxford.xml","metas":{"homepage":"Https://www.ox.ac.uk"}},"upenn":{"title":"University of Pennsylvania","taxon":"Institution","tags":[],"route":"upenn.xml","metas":{"homepage":"Https://www.upenn.edu"}},"uwmadison":{"title":"University of Wisconsin-Madison","taxon":"Institution","tags":[],"route":"uwmadison.xml","metas":{}},"ursulaleguin":{"title":"Ursula K. Le Guin","taxon":"Person","tags":[],"route":"ursulaleguin.xml","metas":{"homepage":"Https://www.ursulakleguin.com"}},"vagoslamprou":{"title":"Vagos Lamprou","taxon":"Person","tags":[],"route":"vagoslamprou.xml","metas":{"institution":"Brown University","position":"PhD Student","homepage":"Https://vagos.github.io"}},"yamatokitahashi":{"title":"Yamato Kitahashi","taxon":"Person","tags":[],"route":"yamatokitahashi.xml","metas":{"original":"北橋日本","position":"Lecturer of Japanese","institution":"The University of Michigan","homepage":"Https://lsa.umich.edu/asian/people/faculty/ykitahas.html"}},"yoshihiromochizuki":{"title":"Yoshihiro Mochizuki","taxon":"Person","tags":[],"route":"yoshihiromochizuki.xml","metas":{"original":"望月良浩","position":"Teaching Professor of Japanese","institution":"The University of Michigan","homepage":"Https://lsa.umich.edu/asian/people/faculty/mochiey.html"}},"yoshimisakakibara":{"title":"Yoshimi Sakakibara","taxon":"Person","tags":[],"route":"yoshimisakakibara.xml","metas":{"original":"榊原芳美","position":"Teaching Professor of Japanese","institution":"The University of Michigan","homepage":"Https://lsa.umich.edu/asian/people/faculty/ysakaki.html"}},"zekaili":{"title":"Zekai Li","taxon":"Person","tags":[],"route":"zekaili.xml","metas":{"institution":"Brown University","position":"Master's Student"}},"zhiyipan":{"title":"Zhiyi Pan","taxon":"Person","tags":[],"route":"zhiyipan.xml","metas":{}},"zzhaoe-0000":{"title":"Home","taxon":null,"tags":[],"route":"index.xml","metas":{}},"zzhaoe-002Z":{"title":"Miscellany","taxon":null,"tags":[],"route":"zzhaoe-002Z.xml","metas":{}},"zzhaoe-0004":{"title":"News","taxon":null,"tags":[],"route":"zzhaoe-0004.xml","metas":{}},"zzhaoe-0003":{"title":"Publications","taxon":null,"tags":[],"route":"zzhaoe-0003.xml","metas":{}},"zzhaoe-0002":{"title":"Software","taxon":null,"tags":[],"route":"zzhaoe-0002.xml","metas":{}},"zzhaoe-000Z":{"title":"Teaching","taxon":null,"tags":[],"route":"zzhaoe-000Z.xml","metas":{}},"zzhaoe-000J":{"title":"Writing","taxon":null,"tags":[],"route":"zzhaoe-000J.xml","metas":{}},"zzhaoe-002R":{"title":"A somewhat and poorly glossed \"The Battle of Brunanburh\" › lines 20b–24a","taxon":null,"tags":[],"route":"zzhaoe-002R.xml","metas":{}},"zzhaoe-002Y":{"title":"A somewhat and poorly glossed \"The Battle of Brunanburh\" › lines 24b–28a","taxon":null,"tags":[],"route":"zzhaoe-002Y.xml","metas":{}},"zzhaoe-002W":{"title":"Second-hand book sellers to avoid online › good, but only once","taxon":null,"tags":[],"route":"zzhaoe-002W.xml","metas":{}},"zzhaoe-002U":{"title":"Second-hand book sellers to avoid online › hard avoid","taxon":null,"tags":[],"route":"zzhaoe-002U.xml","metas":{}},"zzhaoe-002X":{"title":"Second-hand book sellers to avoid online › mixed bag","taxon":null,"tags":[],"route":"zzhaoe-002X.xml","metas":{}},"zzhaoe-002V":{"title":"Second-hand book sellers to avoid online › pretty good","taxon":null,"tags":[],"route":"zzhaoe-002V.xml","metas":{}},"zzhaoe-002Q":{"title":"A somewhat and poorly glossed \"The Battle of Brunanburh\" › lines 17b–20a","taxon":null,"tags":[],"route":"zzhaoe-002Q.xml","metas":{}},"zzhaoe-002J":{"title":"A somewhat and poorly glossed \"The Battle of Brunanburh\" › lines 10b–17a","taxon":null,"tags":[],"route":"zzhaoe-002J.xml","metas":{}},"zzhaoe-002N":{"title":"頭字説明ゲーム › 基本","taxon":null,"tags":[],"route":"zzhaoe-002N.xml","metas":{}},"zzhaoe-002O":{"title":"頭字説明ゲーム › 撥音、促音、拗音、、、","taxon":null,"tags":[],"route":"zzhaoe-002O.xml","metas":{}},"zzhaoe-002P":{"title":"頭字説明ゲーム › バリエーション","taxon":null,"tags":[],"route":"zzhaoe-002P.xml","metas":{}},"zzhaoe-002H":{"title":"A somewhat and poorly glossed \"The Battle of Brunanburh\" › lines 5b–10a","taxon":null,"tags":[],"route":"zzhaoe-002H.xml","metas":{}},"zzhaoe-002G":{"title":"A somewhat and poorly glossed \"The Battle of Brunanburh\" › lines 1–5a","taxon":null,"tags":[],"route":"zzhaoe-002G.xml","metas":{}},"zzhaoe-002C":{"title":"The unwarranted delights › it all just comes together.","taxon":null,"tags":[],"route":"zzhaoe-002C.xml","metas":{}},"zzhaoe-000W":{"title":"On the original Orpheus › Orpheus as known","taxon":null,"tags":[],"route":"zzhaoe-000W.xml","metas":{}},"zzhaoe-000V":{"title":"On the original Orpheus › the successful Orpheus?","taxon":null,"tags":[],"route":"zzhaoe-000V.xml","metas":{}},"zzhaoe-0018":{"title":null,"taxon":"Poem","tags":[],"route":"zzhaoe-0018.xml","metas":{}},"zzhaoe-0019":{"title":null,"taxon":"Poem","tags":[],"route":"zzhaoe-0019.xml","metas":{}},"zzhaoe-0020":{"title":null,"taxon":"Poem","tags":[],"route":"zzhaoe-0020.xml","metas":{}},"zzhaoe-0034":{"title":"News › chronological","taxon":null,"tags":[],"route":"zzhaoe-0034.xml","metas":{}},"zzhaoe-0005":{"title":"Software › ongoing","taxon":null,"tags":[],"route":"zzhaoe-0005.xml","metas":{}},"zzhaoe-0006":{"title":"Software › past","taxon":null,"tags":[],"route":"zzhaoe-0006.xml","metas":{}}}
